[
    {
        "question": "Find next number: 2, 3, 5, 9, 17, ?",
        "options": [
            "33",
            "34",
            "35",
            "36"
        ],
        "answer": "33"
    },
    {
        "question": "If 12 men can do work in 8 days, how many men needed for 4 days?",
        "options": [
            "24",
            "20",
            "16",
            "12"
        ],
        "answer": "24"
    },
    {
        "question": "Average of 6 numbers is 15, total?",
        "options": [
            "60",
            "75",
            "90",
            "100"
        ],
        "answer": "90"
    },
    {
        "question": "Compound interest on 1000 at 10% for 1 year?",
        "options": [
            "100",
            "110",
            "120",
            "150"
        ],
        "answer": "100"
    },
    {
        "question": "Find odd one: 121, 144, 169, 196, 225, 250",
        "options": [
            "121",
            "169",
            "225",
            "250"
        ],
        "answer": "250"
    },
    {
        "question": "Next: 1, 4, 27, 256, ?",
        "options": [
            "625",
            "1024",
            "3125",
            "1296"
        ],
        "answer": "3125"
    },
    {
        "question": "Probability of getting 3 on dice",
        "options": [
            "1/6",
            "1/3",
            "1/2",
            "1/4"
        ],
        "answer": "1/6"
    },
    {
        "question": "LCM of 8, 12, 15",
        "options": [
            "60",
            "120",
            "180",
            "240"
        ],
        "answer": "120"
    },
    {
        "question": "HCF of 36 and 48",
        "options": [
            "6",
            "8",
            "12",
            "16"
        ],
        "answer": "12"
    },
    {
        "question": "Speed 72 km/h, time 5h, distance?",
        "options": [
            "300",
            "320",
            "340",
            "360"
        ],
        "answer": "360"
    },
    {
        "question": "Train 300m, speed 30m/s, time?",
        "options": [
            "5",
            "8",
            "10",
            "12"
        ],
        "answer": "10"
    },
    {
        "question": "35% of 400",
        "options": [
            "120",
            "130",
            "140",
            "150"
        ],
        "answer": "140"
    },
    {
        "question": "Binary of 12",
        "options": [
            "1100",
            "1010",
            "1110",
            "1001"
        ],
        "answer": "1100"
    },
    {
        "question": "Which is not OOP concept",
        "options": [
            "Inheritance",
            "Encapsulation",
            "Compilation",
            "Polymorphism"
        ],
        "answer": "Compilation"
    },
    {
        "question": "Find next: 3, 9, 27, 81, ?",
        "options": [
            "162",
            "243",
            "324",
            "81"
        ],
        "answer": "243"
    },
    {
        "question": "Boat speed 15 km/h, stream 5 km/h, upstream?",
        "options": [
            "10",
            "20",
            "15",
            "5"
        ],
        "answer": "10"
    },
    {
        "question": "Area of circle radius 7 (π=22/7)",
        "options": [
            "144",
            "154",
            "164",
            "174"
        ],
        "answer": "154"
    },
    {
        "question": "Permutation of 3 objects",
        "options": [
            "3",
            "6",
            "9",
            "12"
        ],
        "answer": "6"
    },
    {
        "question": "Which is keyword in C",
        "options": [
            "while",
            "hello",
            "add",
            "number"
        ],
        "answer": "while"
    },
    {
        "question": "Find next: 11, 13, 17, 19, 23, ?",
        "options": [
            "25",
            "27",
            "29",
            "31"
        ],
        "answer": "29"
    }
]